pydsl
tests
