Metadata-Version: 1.1
Name: pydsl
Version: 0.5.4
Summary: Python Domain Specific Language Tools
Home-page: https://github.com/nesaro/pydsl
Author: Nestor Arocha
Author-email: nesaro@gmail.com
License: UNKNOWN
Platform: UNKNOWN
Classifier: License :: OSI Approved :: GNU General Public License v3 (GPLv3)
Classifier: Programming Language :: Python :: 3
